odoo/addons/impersonate_login/README.rst
odoo/addons/impersonate_login/__init__.py
odoo/addons/impersonate_login/__manifest__.py
odoo/addons/impersonate_login/hooks.py
odoo/addons/impersonate_login/i18n/impersonate_login.pot
odoo/addons/impersonate_login/i18n/it.po
odoo/addons/impersonate_login/models/__init__.py
odoo/addons/impersonate_login/models/impersonate_log.py
odoo/addons/impersonate_login/models/ir_http.py
odoo/addons/impersonate_login/models/mail_message.py
odoo/addons/impersonate_login/models/mail_thread.py
odoo/addons/impersonate_login/models/model.py
odoo/addons/impersonate_login/models/res_users.py
odoo/addons/impersonate_login/readme/CONFIGURE.md
odoo/addons/impersonate_login/readme/CONTRIBUTORS.md
odoo/addons/impersonate_login/readme/DESCRIPTION.md
odoo/addons/impersonate_login/readme/USAGE.md
odoo/addons/impersonate_login/security/group.xml
odoo/addons/impersonate_login/security/ir.model.access.csv
odoo/addons/impersonate_login/static/description/icon.png
odoo/addons/impersonate_login/static/description/index.html
odoo/addons/impersonate_login/static/src/js/user_menu.esm.js
odoo/addons/impersonate_login/tests/__init__.py
odoo/addons/impersonate_login/tests/test_impersonate_login.py
odoo/addons/impersonate_login/views/impersonate_log.xml
odoo/addons/impersonate_login/views/res_users.xml
odoo_addon_impersonate_login-19.0.1.0.0.2.dist-info/METADATA
odoo_addon_impersonate_login-19.0.1.0.0.2.dist-info/WHEEL
odoo_addon_impersonate_login-19.0.1.0.0.2.dist-info/top_level.txt
odoo_addon_impersonate_login-19.0.1.0.0.2.dist-info/RECORD
